{
  "$schema": "https://developer.microsoft.com/json-schemas/fabric/item/report/definition/visualContainer/2.7.0/schema.json",
  "name": "f3521a3d7c50f1d4290a",
  "position": {
    "x": 256.16688396349412,
    "y": 60.912646675358538,
    "z": 3000,
    "height": 320.41720990873534,
    "width": 483.12907431551497,
    "tabOrder": 0
  },
  "visual": {
    "visualType": "clusteredColumnChart",
    "query": {
      "queryState": {
        "Category": {
          "projections": [
            {
              "field": {
                "Column": {
                  "Expression": {
                    "SourceRef": {
                      "Entity": "Dim_GIM"
                    }
                  },
                  "Property": "Business Unit"
                }
              },
              "queryRef": "Dim_GIM.Business Unit",
              "nativeQueryRef": "Business Unit",
              "active": true
            }
          ]
        },
        "Y": {
          "projections": [
            {
              "field": {
                "Measure": {
                  "Expression": {
                    "SourceRef": {
                      "Entity": "_Measures"
                    }
                  },
                  "Property": "Profit Margin"
                }
              },
              "queryRef": "_Measures.Profit Margin",
              "nativeQueryRef": "Profit Margin"
            },
            {
              "field": {
                "Measure": {
                  "Expression": {
                    "SourceRef": {
                      "Entity": "_Measures"
                    }
                  },
                  "Property": "Profit Margin minus Sum of Budgeted Growth Margin"
                }
              },
              "queryRef": "_Measures.Profit Margin minus Sum of Budgeted Growth Margin",
              "nativeQueryRef": "Profit Margin minus Sum of Budgeted Growth Margin"
            },
            {
              "field": {
                "NativeVisualCalculation": {
                  "Language": "dax",
                  "Expression": "If(  [Profit Margin minus Sum of Budgeted Growth Margin] >0 , \"#B83C27\", \"#3A913F\")",
                  "Name": "Calculation"
                }
              },
              "queryRef": "select",
              "nativeQueryRef": "Calculation"
            }
          ]
        }
      },
      "sortDefinition": {
        "sort": [
          {
            "field": {
              "Measure": {
                "Expression": {
                  "SourceRef": {
                    "Entity": "_Measures"
                  }
                },
                "Property": "Profit Margin"
              }
            },
            "direction": "Descending"
          }
        ],
        "isDefaultSort": true
      }
    },
    "objects": {
      "categoryAxis": [
        {
          "properties": {
            "axisType": {
              "expr": {
                "Literal": {
                  "Value": "'Categorical'"
                }
              }
            },
            "innerPadding": {
              "expr": {
                "Literal": {
                  "Value": "32L"
                }
              }
            },
            "maxMarginFactor": {
              "expr": {
                "Literal": {
                  "Value": "17L"
                }
              }
            },
            "preferredCategoryWidth": {
              "expr": {
                "Literal": {
                  "Value": "20D"
                }
              }
            }
          }
        }
      ],
      "labels": [
        {
          "properties": {
            "show": {
              "expr": {
                "Literal": {
                  "Value": "true"
                }
              }
            }
          }
        }
      ],
      "layout": [
        {
          "properties": {
            "clusteredGapSize": {
              "expr": {
                "Literal": {
                  "Value": "3D"
                }
              }
            },
            "clusteredGapOverlaps": {
              "expr": {
                "Literal": {
                  "Value": "false"
                }
              }
            }
          }
        }
      ],
      "error": [
        {
          "properties": {
            "enabled": {
              "expr": {
                "Literal": {
                  "Value": "false"
                }
              }
            }
          },
          "selector": {
            "metadata": "_Measures.Profit Margin minus Sum of Budgeted Growth Margin"
          }
        }
      ],
      "dataPoint": [
        {
          "properties": {
            "borderShow": {
              "expr": {
                "Literal": {
                  "Value": "false"
                }
              }
            },
            "borderColorMatchFill": {
              "expr": {
                "Literal": {
                  "Value": "false"
                }
              }
            }
          },
          "selector": {
            "metadata": "_Measures.Profit Margin"
          }
        }
      ]
    },
    "visualContainerObjects": {
      "border": [
        {
          "properties": {
            "show": {
              "expr": {
                "Literal": {
                  "Value": "true"
                }
              }
            },
            "radius": {
              "expr": {
                "Literal": {
                  "Value": "4D"
                }
              }
            },
            "color": {
              "solid": {
                "color": {
                  "expr": {
                    "ThemeDataColor": {
                      "ColorId": 0,
                      "Percent": -0.1
                    }
                  }
                }
              }
            }
          }
        }
      ],
      "title": [
        {
          "properties": {
            "text": {
              "expr": {
                "Literal": {
                  "Value": "'AC Profit Margin vs Budget'"
                }
              }
            }
          }
        }
      ],
      "subTitle": [
        {
          "properties": {
            "text": {
              "expr": {
                "Literal": {
                  "Value": "'By Business Unit'"
                }
              }
            }
          }
        }
      ]
    },
    "drillFilterOtherVisuals": true
  },
  "filterConfig": {
    "filters": [
      {
        "name": "85c202808ee6e0ac1c4d",
        "field": {
          "Column": {
            "Expression": {
              "SourceRef": {
                "Entity": "Dim_GIM"
              }
            },
            "Property": "Business Unit"
          }
        },
        "type": "Categorical"
      },
      {
        "name": "5aee29a3fef217d6c5b5",
        "field": {
          "Measure": {
            "Expression": {
              "SourceRef": {
                "Entity": "_Measures"
              }
            },
            "Property": "Profit Margin"
          }
        },
        "type": "Advanced"
      },
      {
        "name": "1143cf3454f9d5da07bb",
        "field": {
          "Measure": {
            "Expression": {
              "SourceRef": {
                "Entity": "_Measures"
              }
            },
            "Property": "Profit Margin minus Sum of Budgeted Growth Margin"
          }
        },
        "type": "Advanced"
      }
    ]
  }
}