{
  "$schema": "https://developer.microsoft.com/json-schemas/fabric/item/report/definition/bookmark/2.1.0/schema.json",
  "displayName": "Playbook by Role",
  "name": "c0eed1a5ede7ae4d6d02",
  "options": {
    "applyOnlyToTargetVisuals": true,
    "targetVisualNames": [
      "fe9742333088ece1e0b6",
      "006018989f8cd6db9388",
      "2145016dea18612d4643",
      "4acabc18005c250d6f38",
      "517798c70a9a35d9e134",
      "cc7b3a95a5ab407a3b85",
      "96868d5d820b51e610ba"
    ]
  },
  "explorationState": {
    "version": "1.3",
    "activeSection": "dc23a6f18b1cdd8010a5",
    "filters": {
      "byName": {
        "6cf00d88a225a5cdff64": {
          "name": "6cf00d88a225a5cdff64",
          "type": "Categorical",
          "expression": {
            "Column": {
              "Expression": {
                "SourceRef": {
                  "Entity": "Dim_GIM"
                }
              },
              "Property": "DeleteFlag"
            }
          },
          "howCreated": 1
        },
        "f9439439782296ce1ae6": {
          "name": "f9439439782296ce1ae6",
          "type": "Categorical",
          "filter": {
            "Version": 2,
            "From": [
              {
                "Name": "d",
                "Entity": "Dim_GIM",
                "Type": 0
              }
            ],
            "Where": [
              {
                "Condition": {
                  "Not": {
                    "Expression": {
                      "In": {
                        "Expressions": [
                          {
                            "Column": {
                              "Expression": {
                                "SourceRef": {
                                  "Source": "d"
                                }
                              },
                              "Property": "Business Unit"
                            }
                          }
                        ],
                        "Values": [
                          [
                            {
                              "Literal": {
                                "Value": "'Trauma Other'"
                              }
                            }
                          ]
                        ]
                      }
                    }
                  }
                }
              }
            ]
          },
          "expression": {
            "Column": {
              "Expression": {
                "SourceRef": {
                  "Entity": "Dim_GIM"
                }
              },
              "Property": "Business Unit"
            }
          },
          "howCreated": 1
        }
      }
    },
    "sections": {
      "dc23a6f18b1cdd8010a5": {
        "visualContainers": {
          "5b1a17f12b07805334ec": {
            "singleVisual": {
              "visualType": "textbox",
              "objects": {}
            }
          },
          "bc8888f1122047dd4de0": {
            "singleVisual": {
              "visualType": "shape",
              "objects": {}
            }
          },
          "f3233033c31035bab726": {
            "singleVisual": {
              "visualType": "actionButton",
              "objects": {}
            }
          },
          "2145016dea18612d4643": {
            "filters": {
              "byExpr": [
                {
                  "name": "372552208f913de0de61",
                  "type": "Categorical",
                  "expression": {
                    "Column": {
                      "Expression": {
                        "SourceRef": {
                          "Entity": "Dim_Phase"
                        }
                      },
                      "Property": "Phase"
                    }
                  },
                  "howCreated": 0
                },
                {
                  "name": "2c0f94ca59b76ac42968",
                  "type": "Categorical",
                  "expression": {
                    "Column": {
                      "Expression": {
                        "SourceRef": {
                          "Entity": "Dim_Phase"
                        }
                      },
                      "Property": "Objective"
                    }
                  },
                  "howCreated": 0
                },
                {
                  "name": "df3749b89dc37c5bff3c",
                  "type": "Advanced",
                  "expression": {
                    "Column": {
                      "Expression": {
                        "SourceRef": {
                          "Entity": "Dim_Phase"
                        }
                      },
                      "Property": "Phase ID"
                    }
                  },
                  "howCreated": 0
                }
              ]
            },
            "singleVisual": {
              "visualType": "tableEx",
              "objects": {},
              "orderBy": [
                {
                  "Direction": 1,
                  "Expression": {
                    "Column": {
                      "Expression": {
                        "SourceRef": {
                          "Entity": "Dim_Phase"
                        }
                      },
                      "Property": "Phase ID"
                    }
                  }
                }
              ],
              "display": {
                "mode": "hidden"
              }
            }
          },
          "cc7b3a95a5ab407a3b85": {
            "filters": {
              "byExpr": [
                {
                  "name": "e949b6444cae21a441e6",
                  "type": "Advanced",
                  "expression": {
                    "Column": {
                      "Expression": {
                        "SourceRef": {
                          "Entity": "Dim_PhaseActivity"
                        }
                      },
                      "Property": "Phase Activity ID"
                    }
                  },
                  "howCreated": 0
                },
                {
                  "name": "9c742ce3b905315e9232",
                  "type": "Categorical",
                  "expression": {
                    "Column": {
                      "Expression": {
                        "SourceRef": {
                          "Entity": "Dim_Phase"
                        }
                      },
                      "Property": "Phase"
                    }
                  },
                  "howCreated": 0
                },
                {
                  "name": "0a0f6a9ba717c011af65",
                  "type": "Categorical",
                  "expression": {
                    "Column": {
                      "Expression": {
                        "SourceRef": {
                          "Entity": "Dim_PhaseActivity"
                        }
                      },
                      "Property": "Process/Tasks"
                    }
                  },
                  "howCreated": 0
                },
                {
                  "name": "eb470fa38862f13afbd9",
                  "type": "Advanced",
                  "expression": {
                    "Measure": {
                      "Expression": {
                        "SourceRef": {
                          "Entity": "_Measures"
                        }
                      },
                      "Property": "Department (Accountable)"
                    }
                  },
                  "howCreated": 0
                },
                {
                  "name": "835a41bfa0997672d807",
                  "type": "Advanced",
                  "expression": {
                    "Measure": {
                      "Expression": {
                        "SourceRef": {
                          "Entity": "_Measures"
                        }
                      },
                      "Property": "Department (Responsible)"
                    }
                  },
                  "howCreated": 0
                }
              ]
            },
            "singleVisual": {
              "visualType": "tableEx",
              "objects": {},
              "orderBy": [
                {
                  "Direction": 1,
                  "Expression": {
                    "Column": {
                      "Expression": {
                        "SourceRef": {
                          "Entity": "Dim_PhaseActivity"
                        }
                      },
                      "Property": "Process/Tasks"
                    }
                  }
                }
              ]
            }
          },
          "96868d5d820b51e610ba": {
            "filters": {
              "byExpr": [
                {
                  "name": "0d80000e5e8bb9b2267c",
                  "type": "Advanced",
                  "expression": {
                    "Aggregation": {
                      "Expression": {
                        "Column": {
                          "Expression": {
                            "SourceRef": {
                              "Entity": "Dim_Phase"
                            }
                          },
                          "Property": "Objective"
                        }
                      },
                      "Function": 3
                    }
                  },
                  "howCreated": 0
                },
                {
                  "name": "2250e0807b2202dfa83d",
                  "type": "Categorical",
                  "expression": {
                    "Column": {
                      "Expression": {
                        "SourceRef": {
                          "Entity": "Dim_Phase"
                        }
                      },
                      "Property": "Phase"
                    }
                  },
                  "howCreated": 0
                }
              ]
            },
            "singleVisual": {
              "visualType": "advancedSlicerVisual",
              "objects": {}
            }
          },
          "4acabc18005c250d6f38": {
            "filters": {
              "byExpr": [
                {
                  "name": "e0b1d0a345ee52df9192",
                  "type": "Advanced",
                  "expression": {
                    "Column": {
                      "Expression": {
                        "SourceRef": {
                          "Entity": "Dim_PhaseActivity"
                        }
                      },
                      "Property": "Phase Activity ID"
                    }
                  },
                  "howCreated": 0
                },
                {
                  "name": "83c9cd73f27885128711",
                  "type": "Categorical",
                  "expression": {
                    "Column": {
                      "Expression": {
                        "SourceRef": {
                          "Entity": "Dim_Phase"
                        }
                      },
                      "Property": "Phase"
                    }
                  },
                  "howCreated": 0
                },
                {
                  "name": "51eae6ec80901f58b449",
                  "type": "Categorical",
                  "expression": {
                    "Column": {
                      "Expression": {
                        "SourceRef": {
                          "Entity": "Dim_PhaseActivity"
                        }
                      },
                      "Property": "Process/Tasks"
                    }
                  },
                  "howCreated": 0
                },
                {
                  "name": "2c39e21983c9f9148bcd",
                  "type": "Advanced",
                  "expression": {
                    "Measure": {
                      "Expression": {
                        "SourceRef": {
                          "Entity": "_Measures"
                        }
                      },
                      "Property": "Department (Accountable)"
                    }
                  },
                  "howCreated": 0
                },
                {
                  "name": "c3f51df4946d3c4d46e0",
                  "type": "Advanced",
                  "expression": {
                    "Measure": {
                      "Expression": {
                        "SourceRef": {
                          "Entity": "_Measures"
                        }
                      },
                      "Property": "Department (Responsible)"
                    }
                  },
                  "howCreated": 0
                }
              ]
            },
            "singleVisual": {
              "visualType": "tableEx",
              "objects": {},
              "orderBy": [
                {
                  "Direction": 1,
                  "Expression": {
                    "Column": {
                      "Expression": {
                        "SourceRef": {
                          "Entity": "Dim_PhaseActivity"
                        }
                      },
                      "Property": "Phase Activity ID"
                    }
                  }
                }
              ]
            }
          },
          "517798c70a9a35d9e134": {
            "filters": {
              "byExpr": [
                {
                  "name": "49152179987aea4221ae",
                  "type": "Categorical",
                  "expression": {
                    "Column": {
                      "Expression": {
                        "SourceRef": {
                          "Entity": "Dim_Role"
                        }
                      },
                      "Property": "Role Name"
                    }
                  },
                  "howCreated": 0
                }
              ]
            },
            "singleVisual": {
              "visualType": "slicer",
              "objects": {
                "merge": {
                  "general": [
                    {
                      "properties": {
                        "filter": {
                          "filter": {
                            "Version": 2,
                            "From": [
                              {
                                "Name": "d",
                                "Entity": "Dim_Role",
                                "Type": 0
                              }
                            ],
                            "Where": [
                              {
                                "Condition": {
                                  "In": {
                                    "Expressions": [
                                      {
                                        "Column": {
                                          "Expression": {
                                            "SourceRef": {
                                              "Source": "d"
                                            }
                                          },
                                          "Property": "Role Name"
                                        }
                                      }
                                    ],
                                    "Values": [
                                      [
                                        {
                                          "Literal": {
                                            "Value": "'Change Analyst II'"
                                          }
                                        }
                                      ]
                                    ]
                                  }
                                }
                              }
                            ]
                          }
                        }
                      }
                    }
                  ],
                  "data": [
                    {
                      "properties": {
                        "mode": {
                          "expr": {
                            "Literal": {
                              "Value": "'Dropdown'"
                            }
                          }
                        }
                      }
                    }
                  ],
                  "selection": [
                    {
                      "properties": {
                        "strictSingleSelect": {
                          "expr": {
                            "Literal": {
                              "Value": "true"
                            }
                          }
                        }
                      }
                    }
                  ]
                }
              },
              "activeProjections": {
                "Values": [
                  {
                    "Column": {
                      "Expression": {
                        "SourceRef": {
                          "Entity": "Dim_Role"
                        }
                      },
                      "Property": "Role Name"
                    }
                  }
                ]
              }
            }
          },
          "bfb14af9e5b69955e95d": {
            "singleVisual": {
              "visualType": "bookmarkNavigator",
              "objects": {}
            }
          }
        },
        "visualContainerGroups": {
          "ea5803f1b1b7e0c78770": {
            "isHidden": true
          },
          "4c2ff6bfeeb47db2bf0e": {
            "children": {
              "006018989f8cd6db9388": {
                "isHidden": true
              },
              "fe9742333088ece1e0b6": {
                "isHidden": false
              }
            }
          }
        }
      }
    },
    "objects": {
      "merge": {
        "outspacePane": [
          {
            "properties": {
              "expanded": {
                "expr": {
                  "Literal": {
                    "Value": "false"
                  }
                }
              }
            }
          }
        ]
      }
    }
  }
}