{
  "$schema": "https://developer.microsoft.com/json-schemas/fabric/item/report/definition/visualContainer/2.7.0/schema.json",
  "name": "de13f53d32ce1a84be7b",
  "position": {
    "x": 0,
    "y": 51.431219503330205,
    "z": 9000,
    "height": 64.289024379162768,
    "width": 239.87860394537176,
    "tabOrder": 8000
  },
  "visual": {
    "visualType": "slicer",
    "query": {
      "queryState": {
        "Values": {
          "projections": [
            {
              "field": {
                "Column": {
                  "Expression": {
                    "SourceRef": {
                      "Entity": "Dim_Calendar"
                    }
                  },
                  "Property": "MonthEnding"
                }
              },
              "queryRef": "Dim_Calendar.MonthEnding",
              "nativeQueryRef": "MonthEnding",
              "active": true
            }
          ]
        }
      }
    },
    "objects": {
      "data": [
        {
          "properties": {
            "mode": {
              "expr": {
                "Literal": {
                  "Value": "'Dropdown'"
                }
              }
            },
            "isInvertedSelectionMode": {
              "expr": {
                "Literal": {
                  "Value": "true"
                }
              }
            }
          }
        }
      ],
      "selection": [
        {
          "properties": {
            "selectAllCheckboxEnabled": {
              "expr": {
                "Literal": {
                  "Value": "true"
                }
              }
            },
            "singleSelect": {
              "expr": {
                "Literal": {
                  "Value": "false"
                }
              }
            }
          }
        }
      ],
      "general": [
        {
          "properties": {}
        }
      ]
    },
    "drillFilterOtherVisuals": true
  },
  "parentGroupName": "366f0ee87cdd16bdbe4d"
}