{
  "$schema": "https://developer.microsoft.com/json-schemas/fabric/item/report/definition/visualContainer/2.8.0/schema.json",
  "name": "02a648a23908b3054180",
  "position": {
    "x": 0,
    "y": 60.377358490566039,
    "z": 12000,
    "height": 64,
    "width": 240.167714884696,
    "tabOrder": 12000
  },
  "visual": {
    "visualType": "slicer",
    "query": {
      "queryState": {
        "Values": {
          "projections": [
            {
              "field": {
                "Column": {
                  "Expression": {
                    "SourceRef": {
                      "Entity": "Dim_Calendar"
                    }
                  },
                  "Property": "MonthEnding"
                }
              },
              "queryRef": "Dim_Calendar.MonthEnding",
              "nativeQueryRef": "MonthEnding",
              "active": true
            }
          ]
        }
      }
    },
    "objects": {
      "data": [
        {
          "properties": {
            "mode": {
              "expr": {
                "Literal": {
                  "Value": "'Dropdown'"
                }
              }
            }
          }
        }
      ],
      "selection": [
        {
          "properties": {
            "selectAllCheckboxEnabled": {
              "expr": {
                "Literal": {
                  "Value": "true"
                }
              }
            },
            "singleSelect": {
              "expr": {
                "Literal": {
                  "Value": "false"
                }
              }
            }
          }
        }
      ],
      "general": [
        {
          "properties": {}
        }
      ]
    },
    "drillFilterOtherVisuals": true
  },
  "filterConfig": {
    "filters": [
      {
        "name": "6bed282eb4d37140004d",
        "field": {
          "Column": {
            "Expression": {
              "SourceRef": {
                "Entity": "Dim_Calendar"
              }
            },
            "Property": "MonthEnding"
          }
        },
        "type": "Categorical"
      }
    ]
  }
}